{
  "cards": [
    {
      "id": "905b",
      "cardNumber": "1234 5678 9101 0101",
      "cardHolder": "Giovana Zopelaro",
      "validity": "06/12",
      "cvv": "123",
      "cardType": "default",
      "backgroundColor": "#12C2E9",
      "textColor": "#fff"
    },
    {
      "id": "38c3",
      "cardNumber": "5765 8756 7576 5757",
      "cardHolder": "Sarah Goulart",
      "validity": "12/12",
      "cvv": "123",
      "cardType": "default",
      "backgroundColor": "#A5FF32",
      "textColor": "#000000"
    }
  ]
}
